LICENSE
pytoolkit/__init__.py
pytoolkit/basics.py
pytoolkit/check.py
pytoolkit/converter.py
pytoolkit/env.py
pytoolkit/hashing.py
pytoolkit/mixins.py
pytoolkit/net.py
pytoolkit/transform.py
pytoolkit42-0.1.2.dist-info/LICENSE
pytoolkit42-0.1.2.dist-info/WHEEL
pytoolkit42-0.1.2.dist-info/METADATA
pytoolkit42-0.1.2.dist-info/RECORD
