Metadata-Version: 2.1
Name: pytoolkit42
Version: 0.1.2
Summary: Collection of useful utilities and tools for python projects
Home-page: https://github.com/HazardDede/pytoolkit
License: MIT
Keywords: library,tools,python,utility,mixins,decorators
Author: Dennis Muth
Author-email: d.muth@gmx.net
Maintainer: Dennis Muth
Maintainer-email: d.muth@gmx.net
Requires-Python: >=3.6,<4.0
Classifier: Development Status :: 3 - Alpha
Classifier: Intended Audience :: Developers
Classifier: License :: OSI Approved :: MIT License
Classifier: Programming Language :: Python :: 3
Classifier: Programming Language :: Python :: 3.6
Classifier: Programming Language :: Python :: 3.7
Classifier: Programming Language :: Python :: 3.8
Classifier: Programming Language :: Python :: 3.9
Classifier: Topic :: Utilities
Requires-Dist: fastcore (>=1.3.18,<2.0.0)
Requires-Dist: typeguard (>=2.10.0,<3.0.0)
Project-URL: Documentation, https://github.com/HazardDede/pytoolkit
Project-URL: Repository, https://github.com/HazardDede/pytoolkit
